README.rst
setup.cfg
setup.py
bin/bandicoot
lib/bandicoot/__init__.py
lib/bandicoot/cli/__init__.py
lib/bandicoot/cli/api.py
lib/bandicoot/cli/cli.py
lib/bandicoot/exceptions/__init__.py
lib/bandicoot/parser/__init__.py
lib/bandicoot/parser/lex.py
lib/bandicoot/parser/parsetab.py
lib/bandicoot/parser/yacc.py
lib/bandicoot/plugins/__init__.py
lib/bandicoot/plugins/builtins.py
lib/bandicoot/restapi/__init__.py
lib/bandicoot/restapi/routes.py
lib/bandicoots.egg-info/PKG-INFO
lib/bandicoots.egg-info/SOURCES.txt
lib/bandicoots.egg-info/dependency_links.txt
lib/bandicoots.egg-info/requires.txt
lib/bandicoots.egg-info/top_level.txt