Metadata-Version: 1.1
Name: bandicoots
Version: 0.1.0
Summary: The command line and control center of a Data Center or Cloud.
Home-page: https://github.com/starboarder2001/bandicoot
Author: David Whiteside
Author-email: david@davidwhiteside.com
License: MIT
Platform: UNKNOWN
Classifier: Environment :: Console
Classifier: Intended Audience :: Developers
Classifier: Intended Audience :: Information Technology
Classifier: Intended Audience :: System Administrators
Classifier: License :: OSI Approved :: MIT License
Classifier: Natural Language :: English
Classifier: Operating System :: POSIX
Classifier: Programming Language :: Python :: 2.6
Classifier: Programming Language :: Python :: 2.7
Classifier: Topic :: System :: Installation/Setup
Classifier: Topic :: System :: Systems Administration
Classifier: Topic :: Utilities
